{
  "id": "10.1016_j.jacr.2021.10.007",
  "theme": "imagerie",
  "type_etude": "inconnu",
  "message_clinique": "Do‑It‑Yourself Business Intelligence for the Radiologist: A Practical Guide",
  "statut": "brouillon",
  "pmid": "34852270",
  "sources_snapshot": "[{\"label\": \"DOI\", \"url\": \"https://doi.org/10.1016/j.jacr.2021.10.007\"}, {\"label\": \"PubMed\", \"url\": \"https://pubmed.ncbi.nlm.nih.gov/34852270/\"}, {\"label\": \"Éditeur\", \"url\": \"https://www.jacr.org/article/S1546-1440(21)00867-X/abstract\"}]"
}
