{
  "id": "10.2519/jospt.2014.5108",
  "theme": "cervicalgie",
  "type_etude": "inconnu",
  "message_clinique": "Une séance de dry needling diminue la douleur et améliore l’amplitude cervicale à court terme chez cervicalgie mécanique aiguë.",
  "statut": "valide",
  "doi_url": "https://doi.org/10.2519/jospt.2014.5108",
  "pmid": "24568260",
  "publication_date": "2014-01-01",
  "last_verified": "2025-09-19",
  "retraction_status": "ok",
  "evidence_level": {
    "scale": "unknown",
    "value": "unknown",
    "justification": "Une séance de dry needling diminue la douleur et améliore l’amplitude cervicale à court terme chez cervicalgie mécanique aiguë."
  },
  "sources_snapshot": "[{\"title\": \"Publisher page\", \"url\": \"https://doi.org/10.2519/jospt.2014.5108\", \"publisher\": \"Journal of Orthopaedic & Sports Physical Therapy (JOSPT)\", \"accessed_at\": \"2025-09-19\", \"strength\": 3}, {\"title\": \"PubMed\", \"url\": \"https://pubmed.ncbi.nlm.nih.gov/24568260/\", \"publisher\": \"NLM / PubMed\", \"accessed_at\": \"2025-09-19\", \"strength\": 2}]"
}
